{
  "version": 1,
  "generatedAt": "2026-07-01T15:56:49.529Z",
  "summary": {
    "total": 18,
    "up": 16,
    "degraded": 0,
    "down": 2
  },
  "services": {
    "spirzen": {
      "id": "spirzen",
      "domain": "spirzen.ru",
      "url": "https://spirzen.ru",
      "state": "up",
      "httpStatus": 200,
      "latency": 591,
      "checkedAt": "2026-07-01T15:56:47.156Z"
    },
    "search": {
      "id": "search",
      "domain": "search.spirzen.ru",
      "url": "https://search.spirzen.ru",
      "state": "up",
      "httpStatus": 200,
      "latency": 516,
      "checkedAt": "2026-07-01T15:56:47.141Z"
    },
    "assets": {
      "id": "assets",
      "domain": "assets.spirzen.ru",
      "url": "https://assets.spirzen.ru",
      "state": "up",
      "httpStatus": 200,
      "latency": 920,
      "checkedAt": "2026-07-01T15:56:47.546Z"
    },
    "terms": {
      "id": "terms",
      "domain": "terms.spirzen.ru",
      "url": "https://terms.spirzen.ru",
      "state": "up",
      "httpStatus": 200,
      "latency": 867,
      "checkedAt": "2026-07-01T15:56:47.495Z"
    },
    "lab": {
      "id": "lab",
      "domain": "lab.spirzen.ru",
      "url": "https://lab.spirzen.ru",
      "state": "up",
      "httpStatus": 200,
      "latency": 1243,
      "checkedAt": "2026-07-01T15:56:47.872Z"
    },
    "exam": {
      "id": "exam",
      "domain": "exam.spirzen.ru",
      "url": "https://exam.spirzen.ru",
      "state": "down",
      "httpStatus": 0,
      "latency": 2540,
      "checkedAt": "2026-07-01T15:56:49.170Z"
    },
    "quiz": {
      "id": "quiz",
      "domain": "quiz.spirzen.ru",
      "url": "https://quiz.spirzen.ru",
      "state": "down",
      "httpStatus": 0,
      "latency": 2541,
      "checkedAt": "2026-07-01T15:56:49.172Z"
    },
    "kids": {
      "id": "kids",
      "domain": "kids.spirzen.ru",
      "url": "https://kids.spirzen.ru",
      "state": "up",
      "httpStatus": 200,
      "latency": 1621,
      "checkedAt": "2026-07-01T15:56:48.253Z"
    },
    "code": {
      "id": "code",
      "domain": "code.spirzen.ru",
      "url": "https://code.spirzen.ru",
      "state": "up",
      "httpStatus": 200,
      "latency": 1758,
      "checkedAt": "2026-07-01T15:56:48.391Z"
    },
    "play": {
      "id": "play",
      "domain": "play.spirzen.ru",
      "url": "https://play.spirzen.ru",
      "state": "up",
      "httpStatus": 200,
      "latency": 1851,
      "checkedAt": "2026-07-01T15:56:48.485Z"
    },
    "html": {
      "id": "html",
      "domain": "html.spirzen.ru",
      "url": "https://html.spirzen.ru",
      "state": "up",
      "httpStatus": 200,
      "latency": 2120,
      "checkedAt": "2026-07-01T15:56:48.755Z"
    },
    "writer": {
      "id": "writer",
      "domain": "writer.spirzen.ru",
      "url": "https://writer.spirzen.ru",
      "state": "up",
      "httpStatus": 200,
      "latency": 2060,
      "checkedAt": "2026-07-01T15:56:48.696Z"
    },
    "schema": {
      "id": "schema",
      "domain": "schema.spirzen.ru",
      "url": "https://schema.spirzen.ru",
      "state": "up",
      "httpStatus": 200,
      "latency": 2214,
      "checkedAt": "2026-07-01T15:56:48.851Z"
    },
    "sql": {
      "id": "sql",
      "domain": "sql.spirzen.ru",
      "url": "https://sql.spirzen.ru",
      "state": "up",
      "httpStatus": 200,
      "latency": 2475,
      "checkedAt": "2026-07-01T15:56:49.113Z"
    },
    "tools": {
      "id": "tools",
      "domain": "tools.spirzen.ru",
      "url": "https://tools.spirzen.ru",
      "state": "up",
      "httpStatus": 200,
      "latency": 2576,
      "checkedAt": "2026-07-01T15:56:49.214Z"
    },
    "color": {
      "id": "color",
      "domain": "color.spirzen.ru",
      "url": "https://color.spirzen.ru",
      "state": "up",
      "httpStatus": 200,
      "latency": 2621,
      "checkedAt": "2026-07-01T15:56:49.260Z"
    },
    "random": {
      "id": "random",
      "domain": "random.spirzen.ru",
      "url": "https://random.spirzen.ru",
      "state": "up",
      "httpStatus": 200,
      "latency": 2753,
      "checkedAt": "2026-07-01T15:56:49.393Z"
    },
    "games": {
      "id": "games",
      "domain": "games.spirzen.ru",
      "url": "https://games.spirzen.ru",
      "state": "up",
      "httpStatus": 200,
      "latency": 2888,
      "checkedAt": "2026-07-01T15:56:49.529Z"
    }
  }
}
