{
  "version": 1,
  "generatedAt": "2026-07-17T19:43:45.539Z",
  "summary": {
    "total": 18,
    "up": 16,
    "degraded": 0,
    "down": 2
  },
  "services": {
    "spirzen": {
      "id": "spirzen",
      "domain": "spirzen.ru",
      "url": "https://spirzen.ru",
      "state": "up",
      "httpStatus": 200,
      "latency": 389,
      "checkedAt": "2026-07-17T19:43:44.246Z"
    },
    "search": {
      "id": "search",
      "domain": "search.spirzen.ru",
      "url": "https://search.spirzen.ru",
      "state": "up",
      "httpStatus": 200,
      "latency": 244,
      "checkedAt": "2026-07-17T19:43:44.183Z"
    },
    "assets": {
      "id": "assets",
      "domain": "assets.spirzen.ru",
      "url": "https://assets.spirzen.ru",
      "state": "up",
      "httpStatus": 200,
      "latency": 377,
      "checkedAt": "2026-07-17T19:43:44.318Z"
    },
    "terms": {
      "id": "terms",
      "domain": "terms.spirzen.ru",
      "url": "https://terms.spirzen.ru",
      "state": "up",
      "httpStatus": 200,
      "latency": 581,
      "checkedAt": "2026-07-17T19:43:44.524Z"
    },
    "lab": {
      "id": "lab",
      "domain": "lab.spirzen.ru",
      "url": "https://lab.spirzen.ru",
      "state": "up",
      "httpStatus": 200,
      "latency": 480,
      "checkedAt": "2026-07-17T19:43:44.424Z"
    },
    "exam": {
      "id": "exam",
      "domain": "exam.spirzen.ru",
      "url": "https://exam.spirzen.ru",
      "state": "down",
      "httpStatus": 0,
      "latency": 1512,
      "checkedAt": "2026-07-17T19:43:45.457Z"
    },
    "quiz": {
      "id": "quiz",
      "domain": "quiz.spirzen.ru",
      "url": "https://quiz.spirzen.ru",
      "state": "down",
      "httpStatus": 0,
      "latency": 1514,
      "checkedAt": "2026-07-17T19:43:45.460Z"
    },
    "kids": {
      "id": "kids",
      "domain": "kids.spirzen.ru",
      "url": "https://kids.spirzen.ru",
      "state": "up",
      "httpStatus": 200,
      "latency": 894,
      "checkedAt": "2026-07-17T19:43:44.841Z"
    },
    "code": {
      "id": "code",
      "domain": "code.spirzen.ru",
      "url": "https://code.spirzen.ru",
      "state": "up",
      "httpStatus": 200,
      "latency": 969,
      "checkedAt": "2026-07-17T19:43:44.917Z"
    },
    "play": {
      "id": "play",
      "domain": "play.spirzen.ru",
      "url": "https://play.spirzen.ru",
      "state": "up",
      "httpStatus": 200,
      "latency": 1037,
      "checkedAt": "2026-07-17T19:43:44.987Z"
    },
    "html": {
      "id": "html",
      "domain": "html.spirzen.ru",
      "url": "https://html.spirzen.ru",
      "state": "up",
      "httpStatus": 200,
      "latency": 1102,
      "checkedAt": "2026-07-17T19:43:45.053Z"
    },
    "writer": {
      "id": "writer",
      "domain": "writer.spirzen.ru",
      "url": "https://writer.spirzen.ru",
      "state": "up",
      "httpStatus": 200,
      "latency": 1181,
      "checkedAt": "2026-07-17T19:43:45.133Z"
    },
    "schema": {
      "id": "schema",
      "domain": "schema.spirzen.ru",
      "url": "https://schema.spirzen.ru",
      "state": "up",
      "httpStatus": 200,
      "latency": 1261,
      "checkedAt": "2026-07-17T19:43:45.214Z"
    },
    "sql": {
      "id": "sql",
      "domain": "sql.spirzen.ru",
      "url": "https://sql.spirzen.ru",
      "state": "up",
      "httpStatus": 200,
      "latency": 1321,
      "checkedAt": "2026-07-17T19:43:45.275Z"
    },
    "tools": {
      "id": "tools",
      "domain": "tools.spirzen.ru",
      "url": "https://tools.spirzen.ru",
      "state": "up",
      "httpStatus": 200,
      "latency": 1394,
      "checkedAt": "2026-07-17T19:43:45.348Z"
    },
    "color": {
      "id": "color",
      "domain": "color.spirzen.ru",
      "url": "https://color.spirzen.ru",
      "state": "up",
      "httpStatus": 200,
      "latency": 1454,
      "checkedAt": "2026-07-17T19:43:45.409Z"
    },
    "random": {
      "id": "random",
      "domain": "random.spirzen.ru",
      "url": "https://random.spirzen.ru",
      "state": "up",
      "httpStatus": 200,
      "latency": 1551,
      "checkedAt": "2026-07-17T19:43:45.507Z"
    },
    "games": {
      "id": "games",
      "domain": "games.spirzen.ru",
      "url": "https://games.spirzen.ru",
      "state": "up",
      "httpStatus": 200,
      "latency": 1582,
      "checkedAt": "2026-07-17T19:43:45.539Z"
    }
  }
}
